{"District_1": {"candidate1": "Bradley Byrne", "candidate2": "Robert Kennedy Jr.", "party1": "Republican", "party2": "Democratic", "share1": "63.1", "share2": "36.8"}, "District_2": {"candidate1": "Martha Roby", "candidate2": "Tabitha Isner", "party1": "Republican", "party2": "Democratic", "share1": "61.4", "share2": "38.4"}, "District_3": {"candidate1": "Mike Rogers", "candidate2": "Mallory Hagan", "party1": "Republican", "party2": "Democratic", "share1": "63.7", "share2": "36.2"}, "District_4": {"candidate1": "Robert Aderholt", "candidate2": "Lee Auman", "party1": "Republican", "party2": "Democratic", "share1": "79.8", "share2": "20.1"}, "District_5": {"candidate1": "Mo Brooks", "candidate2": "Peter Joffrion", "party1": "Republican", "party2": "Democratic", "share1": "61.0", "share2": "38.9"}, "District_6": {"candidate1": "Gary Palmer", "candidate2": "Danner Kline", "party1": "Republican", "party2": "Democratic", "share1": "69.2", "share2": "30.8"}, "District_7": {"candidate1": "Terri Sewell", "candidate2": "4,153", "party1": "Democratic", "party2": "Write-in", "share1": "97.8", "share2": "2.2"}}